ML_master/__init__.py
ML_master/module_utils.py
ML_master-0.9.dist-info/METADATA
ML_master-0.9.dist-info/WHEEL
ML_master-0.9.dist-info/top_level.txt
ML_master-0.9.dist-info/RECORD
